AUTHORS.rst
CONTRIBUTING.rst
HISTORY.rst
LICENSE
MANIFEST.in
README.rst
setup.cfg
setup.py
docs/Makefile
docs/authors.rst
docs/conf.py
docs/contributing.rst
docs/history.rst
docs/index.rst
docs/installation.rst
docs/make.bat
docs/readme.rst
docs/usage.rst
gunicorn_cache/__init__.py
gunicorn_cache/redis.py
gunicorn_cache.egg-info/PKG-INFO
gunicorn_cache.egg-info/SOURCES.txt
gunicorn_cache.egg-info/dependency_links.txt
gunicorn_cache.egg-info/not-zip-safe
gunicorn_cache.egg-info/requires.txt
gunicorn_cache.egg-info/top_level.txt
tests/__init__.py
tests/test_gunicorn_cache.py