Metadata-Version: 1.1
Name: gunicorn-cache
Version: 0.1.5
Summary: Cache worker for gunicorn
Home-page: https://github.com/youngking/gunicorn_cache
Author: Young King
Author-email: yanckin@gmail.com
License: ISCL
Keywords: gunicorn_cache
Platform: UNKNOWN
Classifier: Development Status :: 2 - Pre-Alpha
Classifier: Intended Audience :: Developers
Classifier: License :: OSI Approved :: ISC License (ISCL)
Classifier: Natural Language :: English
Classifier: Programming Language :: Python :: 2
Classifier: Programming Language :: Python :: 2.6
Classifier: Programming Language :: Python :: 2.7
Classifier: Programming Language :: Python :: 3
Classifier: Programming Language :: Python :: 3.3
Classifier: Programming Language :: Python :: 3.4
